aws_acl_helper/__init__.py
aws_acl_helper/aclmatch.py
aws_acl_helper/commands.py
aws_acl_helper/config.py
aws_acl_helper/core.py
aws_acl_helper/listen.py
aws_acl_helper/metadata.py
aws_acl_helper/squid.py
aws_acl_helper/sync.py
aws_acl_helper/version.py
aws_acl_helper-1.1.0.dist-info/DESCRIPTION.rst
aws_acl_helper-1.1.0.dist-info/METADATA
aws_acl_helper-1.1.0.dist-info/RECORD
aws_acl_helper-1.1.0.dist-info/WHEEL
aws_acl_helper-1.1.0.dist-info/entry_points.txt
aws_acl_helper-1.1.0.dist-info/metadata.json
aws_acl_helper-1.1.0.dist-info/top_level.txt
aws_acl_helper-1.1.0.dist-info/version.txt
aws_acl_helper-1.1.0.dist-info/version_full.txt
