Metadata-Version: 2.0
Name: aws-acl-helper
Version: 1.1.0
Summary: Squid external ACL helper that allows use of AWS instance metadata
Home-page: https://github.com/brandond/aws-acl-helper
Author: Brandon Davidson
Author-email: brad@oatmail.org
License: UNKNOWN
Platform: UNKNOWN
Classifier: Development Status :: 5 - Production/Stable
Classifier: Environment :: No Input/Output (Daemon)
Classifier: Framework :: AsyncIO
Classifier: License :: OSI Approved :: Apache Software License
Classifier: Operating System :: POSIX :: Linux
Classifier: Programming Language :: Python :: 3.6
Classifier: Programming Language :: Python :: 3.7
Classifier: Topic :: Internet :: Proxy Servers
Classifier: Topic :: Security
Requires-Python: >=3.6
Requires-Dist: aioredis (>=1.0.0)
Requires-Dist: asyncio
Requires-Dist: boto3 (==1.9.149)
Requires-Dist: botocore (==1.12.149)
Requires-Dist: click
Requires-Dist: configparser (>=3.5.0)
Provides-Extra: dev
Requires-Dist: setuptools-version-command; extra == 'dev'
